{
    "status": "ok",
    "page": 183,
    "data": [
        {
            "id": "EGQK",
            "name": "KINLOSS",
            "country": "United Kingdom of Great Britain and Northern Ireland",
            "lat": 57.6494444,
            "lon": -3.5605556
        },
        {
            "id": "EGQL",
            "name": "LEUCHARS",
            "country": "United Kingdom of Great Britain and Northern Ireland",
            "lat": 56.37266666666667,
            "lon": -2.8685
        },
        {
            "id": "EGQM",
            "name": "BOULMER  (MOD)",
            "country": "United Kingdom of Great Britain and Northern Ireland",
            "lat": 55.42,
            "lon": -1.6008333
        },
        {
            "id": "EGQS",
            "name": "LOSSIEMOUTH",
            "country": "United Kingdom of Great Britain and Northern Ireland",
            "lat": 57.705025000000006,
            "lon": -3.3391361111111113
        },
        {
            "id": "EGSC",
            "name": "CAMBRIDGE",
            "country": "United Kingdom of Great Britain and Northern Ireland",
            "lat": 52.205000000000005,
            "lon": 0.175
        },
        {
            "id": "EGSH",
            "name": "NORWICH",
            "country": "United Kingdom of Great Britain and Northern Ireland",
            "lat": 52.67583333333333,
            "lon": 1.2827777777777778
        },
        {
            "id": "EGSS",
            "name": "LONDON STANSTED",
            "country": "United Kingdom of Great Britain and Northern Ireland",
            "lat": 51.885,
            "lon": 0.23500000000000001
        },
        {
            "id": "EGTC",
            "name": "CRANFIELD",
            "country": "United Kingdom of Great Britain and Northern Ireland",
            "lat": 52.07222222222222,
            "lon": -0.6166666666666667
        },
        {
            "id": "EGTE",
            "name": "EXETER",
            "country": "United Kingdom of Great Britain and Northern Ireland",
            "lat": 50.73429166666667,
            "lon": -3.413811111111111
        },
        {
            "id": "EGUB",
            "name": "BENSON",
            "country": "United Kingdom of Great Britain and Northern Ireland",
            "lat": 51.61503888888889,
            "lon": -1.0958472222222222
        }
    ]
}