{
    "status": "ok",
    "page": 16,
    "data": [
        {
            "id": "KJOT",
            "name": "JOLIET RGNL",
            "country": "United States of America",
            "lat": 41.51765833333333,
            "lon": -88.17552222222223
        },
        {
            "id": "KIKK",
            "name": "GREATER KANKAKEE",
            "country": "United States of America",
            "lat": 41.07138888888889,
            "lon": -87.84627777777777
        },
        {
            "id": "KLWV",
            "name": "LAWRENCEVILLE-VINCENNES INTL",
            "country": "United States of America",
            "lat": 38.76427777777778,
            "lon": -87.60549999999999
        },
        {
            "id": "KMQB",
            "name": "MACOMB MUNI",
            "country": "United States of America",
            "lat": 40.52008333333333,
            "lon": -90.6523888888889
        },
        {
            "id": "KMWA",
            "name": "WILLIAMSON COUNTY RGNL",
            "country": "United States of America",
            "lat": 37.75497222222222,
            "lon": -89.01108333333333
        },
        {
            "id": "KMTO",
            "name": "COLES COUNTY MEMORIAL",
            "country": "United States of America",
            "lat": 39.47788888888889,
            "lon": -88.27997222222223
        },
        {
            "id": "KMLI",
            "name": "QUAD CITY INTL",
            "country": "United States of America",
            "lat": 41.448277777777776,
            "lon": -90.50752777777778
        },
        {
            "id": "KMVN",
            "name": "MOUNT VERNON",
            "country": "United States of America",
            "lat": 38.32336111111111,
            "lon": -88.85849999999999
        },
        {
            "id": "KOLY",
            "name": "OLNEY-NOBLE",
            "country": "United States of America",
            "lat": 38.72182777777778,
            "lon": -88.17643333333334
        },
        {
            "id": "KPWK",
            "name": "CHICAGO EXECUTIVE",
            "country": "United States of America",
            "lat": 42.11427777777778,
            "lon": -87.90152777777779
        }
    ]
}